nonebot_plugin_kanonbot/__init__.py
nonebot_plugin_kanonbot/bot_run.py
nonebot_plugin_kanonbot/config.py
nonebot_plugin_kanonbot/plugins.py
nonebot_plugin_kanonbot/tools.py
nonebot_plugin_kanonbot-0.3.2.dist-info/LICENSE
nonebot_plugin_kanonbot-0.3.2.dist-info/METADATA
nonebot_plugin_kanonbot-0.3.2.dist-info/WHEEL
nonebot_plugin_kanonbot-0.3.2.dist-info/top_level.txt
nonebot_plugin_kanonbot-0.3.2.dist-info/RECORD
