Metadata-Version: 2.1
Name: nonebot-plugin-kanonbot
Version: 0.3.2
Summary: nonebot plugin kanonbot
Home-page: https://github.com/SuperGuGuGu/nonebot_plugin_kanonbot
Author: SuperGuGuGu
Author-email: 13680478000@163.com
Requires-Python: >=3.8
License-File: LICENSE
Requires-Dist: pillow (>=9.5.0)
Requires-Dist: httpx (>=0.24.0)
Requires-Dist: requests (>=2.31.0)
Requires-Dist: toml (>=0.10.2)
Requires-Dist: nonebot2 (>=2.0.0)
Requires-Dist: nonebot-adapter-qq (>=1.3.0)
Requires-Dist: numpy (>=1.26.3)
